README.rst
authorization_levels.py
setup.py
datapunt_authorization_levels.egg-info/PKG-INFO
datapunt_authorization_levels.egg-info/SOURCES.txt
datapunt_authorization_levels.egg-info/dependency_links.txt
datapunt_authorization_levels.egg-info/top_level.txt