Metadata-Version: 1.1
Name: datapunt-authorization-levels
Version: 0.1.1
Summary: Datapunt authorization levels
Home-page: https://github.com/DatapuntAmsterdam/autorization_levels
Author: Amsterdam Datapunt
Author-email: datapunt.ois@amsterdam.nl
License: Mozilla Public License Version 2.0
Platform: UNKNOWN
Classifier: Development Status :: 3 - Alpha
Classifier: Intended Audience :: Developers
Classifier: Natural Language :: English
Classifier: Topic :: System :: Systems Administration :: Authentication/Directory
Classifier: License :: OSI Approved :: Mozilla Public License 2.0 (MPL 2.0)
Classifier: Programming Language :: Python
Classifier: Programming Language :: Python :: 3.4
Classifier: Programming Language :: Python :: 3.5
Classifier: Programming Language :: Python :: 3.6
